MANIFEST.in
README.rst
base.cfg
buildout.cfg
constraints_plone51.txt
constraints_plone52.txt
requirements.txt
setup.cfg
setup.py
test_plone51.cfg
test_plone52.cfg
docs/HISTORY.rst
docs/INSTALL.txt
docs/LICENSE.GPL
docs/LICENSE.txt
docs/rer-logo.png
docs/images/rer.cookieconsent-0.1.0-01.png
docs/images/rer.cookieconsent-0.1.0-02.png
docs/images/rer.cookieconsent-0.1.0-03.png
rer/__init__.py
rer.cookieconsent.egg-info/PKG-INFO
rer.cookieconsent.egg-info/SOURCES.txt
rer.cookieconsent.egg-info/dependency_links.txt
rer.cookieconsent.egg-info/entry_points.txt
rer.cookieconsent.egg-info/namespace_packages.txt
rer.cookieconsent.egg-info/not-zip-safe
rer.cookieconsent.egg-info/requires.txt
rer.cookieconsent.egg-info/top_level.txt
rer/cookieconsent/__init__.py
rer/cookieconsent/config.py
rer/cookieconsent/configure.zcml
rer/cookieconsent/init_cookies.py
rer/cookieconsent/interfaces.py
rer/cookieconsent/setuphandlers.py
rer/cookieconsent/testing.py
rer/cookieconsent/utils.py
rer/cookieconsent/vocabularies.py
rer/cookieconsent/browser/__init__.py
rer/cookieconsent/browser/configure.zcml
rer/cookieconsent/browser/dashboard.pt
rer/cookieconsent/browser/dashboard.py
rer/cookieconsent/browser/util.py
rer/cookieconsent/browser/resources/cookie.png
rer/cookieconsent/browser/resources/cookiepolicy.css
rer/cookieconsent/browser/resources/cookiepolicy.js
rer/cookieconsent/browser/resources/utils.js
rer/cookieconsent/controlpanel/__init__.py
rer/cookieconsent/controlpanel/configure.zcml
rer/cookieconsent/controlpanel/interfaces.py
rer/cookieconsent/controlpanel/view.py
rer/cookieconsent/exportimport/__init__.py
rer/cookieconsent/exportimport/configure.zcml
rer/cookieconsent/exportimport/handlers.py
rer/cookieconsent/jsconfiguration/__init__.py
rer/cookieconsent/jsconfiguration/banner-configuration-labels.pt
rer/cookieconsent/jsconfiguration/configuration.py
rer/cookieconsent/jsconfiguration/configure.zcml
rer/cookieconsent/jsconfiguration/fields_adapter.py
rer/cookieconsent/locales/rebuildPo.sh
rer/cookieconsent/locales/rer.cookieconsent-manual.pot
rer/cookieconsent/locales/rer.cookieconsent.pot
rer/cookieconsent/locales/de/LC_MESSAGES/rer.cookieconsent.po
rer/cookieconsent/locales/it/LC_MESSAGES/rer.cookieconsent.po
rer/cookieconsent/profiles/default/browserlayer.xml
