Metadata-Version: 2.1
Name: rer.cookieconsent
Version: 0.4.6
Summary: A cookies consent Plone solution; used for European Cookie Law by Emilia Romagna Region
Home-page: http://github.com/PloneGov-IT/rer.cookieconsent
Author: RedTurtle Technology
Author-email: sviluppoplone@redturtle.it
License: GPL
Keywords: plone plonegov cookie-consent cookie-law cookie privacy
Classifier: Framework :: Plone
Classifier: Framework :: Plone :: 4.2
Classifier: Framework :: Plone :: 4.3
Classifier: Programming Language :: Python
Provides-Extra: test
